[
  {
    "name": "NESPico",
    "dropdown": "Projects",
    "priority": 150,
    "post_content": "---\nCheck out the [repo](https://github.com/luxedo/NESPico)"
  },
  {
    "name": "two-neurons-worm",
    "dropdown": "Projects",
    "priority": 90
  },
  {
    "name": "calcuMLator",
    "dropdown": "Projects",
    "priority": 100
  },
  {
    "name": "advent-of-code",
    "dropdown": "Projects",
    "priority": 200
  },
  {
    "name": "smarty-bird",
    "dropdown": "Games",
    "priority": 120
  },
  {
    "name": "minesweeper-almost-from-scratch",
    "dropdown": "Games",
    "priority": 110
  },
  {
    "name": "spacewar-almost-from-scratch",
    "dropdown": "Games",
    "priority": 100
  },
  {
    "name": "asteroids-almost-from-scratch",
    "dropdown": "Games",
    "priority": 90
  },
  {
    "name": "hamurabi-almost-from-scratch",
    "dropdown": "Games",
    "priority": 70
  },
  {
    "name": "pong-almost-from-scratch",
    "dropdown": "Games",
    "priority": 80
  },
  {
    "name": "tetris-almost-from-scratch",
    "dropdown": "Games",
    "priority": 110
  },
  {
    "name": "RPistepper",
    "dropdown": "Libraries",
    "priority": 100,
    "post_content": "---\nCheck out the [repo](https://github.com/luxedo/RPistepper)"
  },
  {
    "name": "RPi_mcp3008",
    "dropdown": "Libraries",
    "priority": 80,
    "post_content": "---\nCheck out the [repo](https://github.com/luxedo/RPi_mcp3008)"
  },
  {
    "name": "fakeRPiGPIO",
    "dropdown": "Libraries",
    "priority": 60,
    "post_content": "---\nCheck out the [repo](https://github.com/luxedo/fakeRPiGPIO)"
  },
  {
    "name": "prettycode",
    "dropdown": "Libraries",
    "priority": 110,
    "post_content": "---\nCheck out the [repo](https://github.com/luxedo/prettycode)"
  },
  {
    "name": "spiky-clouds",
    "dropdown": "Libraries",
    "priority": 120,
    "post_content": "---\nCheck out the [repo](https://github.com/luxedo/prettycode)"
  },
  {
    "name": "node-SPOS",
    "dropdown": "Libraries",
    "priority": 130,
    "post_content": "---\nCheck out the [repo](https://github.com/luxedo/node-SPOS)"
  },
  {
    "name": "SPOS",
    "dropdown": "Libraries",
    "priority": 140,
    "post_content": "---\nCheck out the [repo](https://github.com/luxedo/SPOS)"
  },
  {
    "name": "OCDots",
    "dropdown": "Libraries",
    "priority": 150,
    "post_content": "---\nCheck out the [repo](https://github.com/luxedo/OCDots)"
  },
  {
    "name": "jekyll-theme-potato-hacker",
    "dropdown": "Libraries",
    "priority": 90,
    "post_content": "---\nCheck out the [repo](https://github.com/luxedo/jekyll-theme-potato-hacker)"
  }
]
